{
  "projects": [
    {
      "id": "robot-seguidor",
      "title": "Robot Seguidor de Línea",
      "category": "robotica",
      "description": "Construimos un robot autónomo capaz de seguir una línea negra usando sensores de infrarrojos y programación por bloques en mBlock. El proyecto culminó con una mini-competición entre equipos.",
      "image": "media/images/robot-seguidor.jpg",
      "emoji": "🤖",
      "gradient": "linear-gradient(135deg, #1565c0 0%, #00bcd4 100%)",
      "tags": ["Lego EV3", "mBlock", "Sensores IR"],
      "hasVideo": true,
      "hasPDF": true,
      "date": "2025-03",
      "course": "Nivel 3 · PAI 8-9"
    }
  ],
  "videos": [
    {
      "id": "v1",
      "youtubeId": "dQw4w9WgXcQ",
      "title": "Robot Seguidor de Línea — Competición Final",
      "description": "Demostración del robot en el circuito de pruebas durante la mini-competición entre equipos."
    },
    {
      "id": "v2",
      "youtubeId": "ScMzIvxBSi4",
      "title": "Estación Meteorológica IoT en Acción",
      "description": "Presentación del proyecto IoT ante las familias. Dashboard en tiempo real con datos reales."
    },
    {
      "id": "v3",
      "youtubeId": "ysz5S6PUM-U",
      "title": "Demo Clasificador IA — Reciclaje Inteligente",
      "description": "El modelo de Machine Learning distinguiendo residuos reciclables en tiempo real con la cámara."
    }
  ],
  "images": [
    { "id": "i1", "src": "img/img1.jpg", "alt": "" },
    { "id": "i2", "src": "img/img2.jpg", "alt": "" },
    { "id": "i3", "src": "img/img3.jpg", "alt": "" },
    { "id": "i4", "src": "img/img4.jpg", "alt": "" },
    { "id": "i5", "src": "img/img5.jpg", "alt": "" },
    { "id": "i6", "src": "img/img6.jpg", "alt": "" }
    { "id": "i7", "src": "img/img7.jpg", "alt": "" },
    { "id": "i8", "src": "img/img8.jpg", "alt": "" },
    { "id": "i9", "src": "img/img9.jpg", "alt": "" },
    { "id": "i10", "src": "img/img10.jpg", "alt": "" },
    { "id": "i11", "src": "img/img11.jpg", "alt": "" },
    { "id": "i12", "src": "img/img12.jpg", "alt": "" }
    { "id": "i13", "src": "img/img13.jpg", "alt": "" },
    { "id": "i14", "src": "img/img14.jpg", "alt": "" },
    { "id": "i15", "src": "img/img15.jpg", "alt": "" },
    { "id": "i16", "src": "img/img16.jpg", "alt": "" },
    { "id": "i17", "src": "img/img17.jpg", "alt": "" },
    { "id": "i18", "src": "img/img18.jpg", "alt": "" }
    { "id": "i19", "src": "img/img19.jpg", "alt": "" },
    { "id": "i20", "src": "img/img20.jpg", "alt": "" },
    { "id": "i21", "src": "img/img21.jpg", "alt": "" },
    { "id": "i22", "src": "img/img22.jpg", "alt": "" },
    { "id": "i23", "src": "img/img23.jpg", "alt": "" },
    { "id": "i24", "src": "img/img24.jpg", "alt": "" }





























    
  ],
  "pdfs": [
    {
      "id": "p1",
      "name": "Guía del Proyecto Robot Seguidor.pdf",
      "url": "media/pdfs/guia-robot-seguidor.pdf",
      "size": "1.2 MB",
      "description": "Documentación completa del proyecto de robótica nivel 3."
    },
    {
      "id": "p2",
      "name": "Dossier Estación Meteorológica IoT.pdf",
      "url": "media/pdfs/dossier-iot.pdf",
      "size": "3.4 MB",
      "description": "Memoria técnica del proyecto IoT con ESP32 y dashboard web."
    },
    {
      "id": "p3",
      "name": "Itinerario Formativo 2026-2027.pdf",
      "url": "media/pdfs/itinerario-formativo.pdf",
      "size": "0.8 MB",
      "description": "Programa oficial de la actividad extraescolar completo."
    }
  ]
}
